Metadata-Version: 2.1
Name: QuranDownloader
Version: 1.0.3
Summary: download quran audio easily
Home-page: UNKNOWN
Author: Malik
Author-email: myemail46926213@gmail.com
License: UNKNOWN
Keywords: python,quran,audio,reciter,verses,concurrent
Platform: UNKNOWN
Classifier: Development Status :: 1 - Planning
Classifier: Intended Audience :: Developers
Classifier: Programming Language :: Python :: 3
Classifier: Operating System :: Unix
Classifier: Operating System :: MacOS :: MacOS X
Classifier: Operating System :: Microsoft :: Windows
